pa_latex/__init__.py
pa_latex/example.py
pa_latex/generate.py
pa_latex/save.py
pa_latex-0.1.0.dist-info/METADATA
pa_latex-0.1.0.dist-info/WHEEL
pa_latex-0.1.0.dist-info/RECORD
