Metadata-Version: 2.1
Name: pa-latex
Version: 0.1.0
Summary: A sample package to work with latex
Author: Semyon Lukin
Author-email: lukinsemyon@yandex.ru
Requires-Python: >=3.10,<4.0
Classifier: Programming Language :: Python :: 3
Classifier: Programming Language :: Python :: 3.10
Classifier: Programming Language :: Python :: 3.11
Classifier: Programming Language :: Python :: 3.12
Classifier: Programming Language :: Python :: 3.13
Requires-Dist: pdflatex (>=0.1.3,<0.2.0)
